CASlibrary/Action.py
CASlibrary/Config.py
CASlibrary/Logger.py
CASlibrary/RedisMB.py
CASlibrary/__init__.py
CASlibrary/constants.py
CASlibrary-0.8.2.dist-info/METADATA
CASlibrary-0.8.2.dist-info/WHEEL
CASlibrary-0.8.2.dist-info/top_level.txt
CASlibrary-0.8.2.dist-info/RECORD
