Metadata-Version: 2.1
Name: CASlibrary
Version: 0.8.2
Summary: The universal lib used in the CAS system
Home-page: https://github.com/FF-Woernitz/CAS_library
Author: FF Woernitz
Author-email: technik@ff-woernitz.de
License: UNKNOWN
Platform: UNKNOWN
Classifier: Programming Language :: Python :: 3
Requires-Python: >=3.6
Requires-Dist: setuptools (~=50.3.0)
Requires-Dist: wheel (~=0.35.1)
Requires-Dist: pip (~=20.2.3)
Requires-Dist: redis (~=3.5.3)
Requires-Dist: Logbook (~=1.5.3)
